pyrmute/__init__.py
pyrmute/_migration_manager.py
pyrmute/_protobuf_types.py
pyrmute/_registry.py
pyrmute/_schema_documents.py
pyrmute/_schema_generator.py
pyrmute/_schema_manager.py
pyrmute/_type_inspector.py
pyrmute/_version.py
pyrmute/avro_schema.py
pyrmute/avro_types.py
pyrmute/exceptions.py
pyrmute/migration_hooks.py
pyrmute/migration_testing.py
pyrmute/model_diff.py
pyrmute/model_manager.py
pyrmute/model_version.py
pyrmute/protobuf_schema.py
pyrmute/py.typed
pyrmute/schema_config.py
pyrmute/types.py
pyrmute/typescript_schema.py
pyrmute/cli/__init__.py
pyrmute/cli/_helpers.py
pyrmute/cli/config.py
pyrmute/cli/main.py
pyrmute-0.10.0.dist-info/licenses/LICENSE
pyrmute-0.10.0.dist-info/METADATA
pyrmute-0.10.0.dist-info/WHEEL
pyrmute-0.10.0.dist-info/entry_points.txt
pyrmute-0.10.0.dist-info/top_level.txt
pyrmute-0.10.0.dist-info/RECORD
