Metadata-Version: 2.4
Name: pyrmute
Version: 0.10.0
Summary: Pydantic model migrations and schemas
Author-email: Matt Ferrera <mattferrera@gmail.com>
License: MIT
Project-URL: Homepage, https://github.com/mferrera/pyrmute
Project-URL: Repository, https://github.com/mferrera/pyrmute
Project-URL: Documentation, https://github.com/mferrera/pyrmute
Keywords: pydantic,migration,versioning,schema,jsonschema,avro,protobuf
Classifier: Development Status :: 3 - Alpha
Classifier: Topic :: Utilities
Classifier: Operating System :: POSIX :: Linux
Classifier: Programming Language :: Python :: 3.11
Classifier: Programming Language :: Python :: 3.12
Classifier: Programming Language :: Python :: 3.13
Classifier: Programming Language :: Python :: 3.14
Classifier: Natural Language :: English
Requires-Python: >=3.11
License-File: LICENSE
Requires-Dist: pydantic
Dynamic: license-file
